Workbook

Sheet Strategies
A1: Strategy | B1: Conservative | C1: Growth
A2: Starting Revenue | B2: 1000000 | C2: 1000000
A3: Revenue Growth Rate Year 2 | B3: 0.05 | C3: 0.12
A4: Revenue Growth Rate Year 3 | B4: 0.06 | C4: 0.15
A5: Revenue Growth Rate Year 4 | B5: 0.06 | C5: 0.18
A6: Revenue Growth Rate Year 5 Onwards | B6: 0.05 | C6: 0.25
A7: Gross Margin (%) | B7: 0.38 | C7: 0.4
A8: Marketing as % of revenue | B8: 0.05 | C8: 0.08
A9: Staff costs as % of revenue | B9: 0.15 | C9: 0.18
A10: Other opex as % of revenue | B10: 0.08 | C10: 0.08
A11: Capex as % of revenue (First 5 years) | B11: 0.05 | C11: 0.07
A12: Capex as % of revenue (After 5 years) | B12: 0.03 | C12: 0.045
A13: Tax rate % | B13: 0.2 | C13: 0.2
A14: Opening Cash | B14: 200000 | C14: 200000

Sheet Assumptions
A1: Strategy Selector | B1: Growth
A2: Starting Revenue | B2: =INDEX(Strategies!B2:C2, MATCH($B$1, Strategies!$B$1:$C$1, 0)) -> 1000000
A3: Revenue Growth Rate Year 2 | B3: =INDEX(Strategies!B3:C3, MATCH($B$1, Strategies!$B$1:$C$1, 0)) -> 0.12
A4: Revenue Growth Rate Year 3 | B4: =INDEX(Strategies!B4:C4, MATCH($B$1, Strategies!$B$1:$C$1, 0)) -> 0.15
A5: Revenue Growth Rate Year 4 | B5: =INDEX(Strategies!B5:C5, MATCH($B$1, Strategies!$B$1:$C$1, 0)) -> 0.18
A6: Revenue Growth Rate Year 5 | B6: =INDEX(Strategies!B6:C6, MATCH($B$1, Strategies!$B$1:$C$1, 0)) -> 0.25
A7: Gross Margin (%) | B7: =INDEX(Strategies!B7:C7, MATCH($B$1, Strategies!$B$1:$C$1, 0)) -> 0.4
A8: Marketing as % of revenue | B8: =INDEX(Strategies!B8:C8, MATCH($B$1, Strategies!$B$1:$C$1, 0)) -> 0.08
A9: Staff costs as % of revenue | B9: =INDEX(Strategies!B9:C9, MATCH($B$1, Strategies!$B$1:$C$1, 0)) -> 0.18
A10: Other opex as % of revenue | B10: =INDEX(Strategies!B10:C10, MATCH($B$1, Strategies!$B$1:$C$1, 0)) -> 0.08
A11: Capex as % of revenue (First 5 years) | B11: =INDEX(Strategies!B11:C11, MATCH($B$1, Strategies!$B$1:$C$1, 0)) -> 0.07
A12: Capex as % of revenue (After 5 years) | B12: =INDEX(Strategies!B12:C12, MATCH($B$1, Strategies!$B$1:$C$1, 0)) -> 0.045
A13: Tax rate % | B13: =INDEX(Strategies!B13:C13, MATCH($B$1, Strategies!$B$1:$C$1, 0)) -> 0.2
A14: Opening Cash | B14: =INDEX(Strategies!B14:C14, MATCH($B$1, Strategies!$B$1:$C$1, 0)) -> 200000

Sheet Model
A1: Years | B1: 1 | C1: 2 | D1: 3 | E1: 4 | F1: 5 | G1: 6 | H1: 7 | I1: 8 | J1: 9 | K1: 10
A2: Revenue | B2: =Assumptions!B2 -> 1000000 | C2: =B2*(1+Assumptions!B3) -> 1120000 | D2: =C2*(1+Assumptions!B4) -> 1288000 | E2: =D2*(1+Assumptions!B5) -> 1519840 | F2: =E2*(1+Assumptions!$B$6) -> 1899800 | G2: =F2*(1+Assumptions!$B$6) -> 2374750 | H2: =G2*(1+Assumptions!$B$6) -> 2968437.5 | I2: =H2*(1+Assumptions!$B$6) -> 3710546.9 | J2: =I2*(1+Assumptions!$B$6) -> 4638183.6 | K2: =J2*(1+Assumptions!$B$6) -> 5797729.5
A4: COGS | B4: =B2*(1-Assumptions!$B$7) -> 600000 | C4: =C2*(1-Assumptions!$B$7) -> 672000 | D4: =D2*(1-Assumptions!$B$7) -> 772800 | E4: =E2*(1-Assumptions!$B$7) -> 911904 | F4: =F2*(1-Assumptions!$B$7) -> 1139880 | G4: =G2*(1-Assumptions!$B$7) -> 1424850 | H4: =H2*(1-Assumptions!$B$7) -> 1781062.5 | I4: =I2*(1-Assumptions!$B$7) -> 2226328.1 | ... K4: =K2*(1-Assumptions!$B$7) -> 3478637.7
A5: Gross profit | B5: =B2-B4 -> 400000 | C5: =C2-C4 -> 448000 | D5: =D2-D4 -> 515200 | E5: =E2-E4 -> 607936 | F5: =F2-F4 -> 759920 | G5: =G2-G4 -> 949900 | H5: =H2-H4 -> 1187375 | I5: =I2-I4 -> 1484218.8 | ... K5: =K2-K4 -> 2319091.8
A7: Marketing expense | B7: =B2*Assumptions!$B$8 -> 80000 | C7: =C2*Assumptions!$B$8 -> 89600 | D7: =D2*Assumptions!$B$8 -> 103040 | E7: =E2*Assumptions!$B$8 -> 121587.2 | F7: =F2*Assumptions!$B$8 -> 151984 | G7: =G2*Assumptions!$B$8 -> 189980 | H7: =H2*Assumptions!$B$8 -> 237475 | I7: =I2*Assumptions!$B$8 -> 296843.75 | ... K7: =K2*Assumptions!$B$8 -> 463818.36
A8: Staff costs | B8: =B2*Assumptions!$B$9 -> 180000 | C8: =C2*Assumptions!$B$9 -> 201600 | D8: =D2*Assumptions!$B$9 -> 231840 | E8: =E2*Assumptions!$B$9 -> 273571.2 | F8: =F2*Assumptions!$B$9 -> 341964 | G8: =G2*Assumptions!$B$9 -> 427455 | H8: =H2*Assumptions!$B$9 -> 534318.75 | I8: =I2*Assumptions!$B$9 -> 667898.44 | ... K8: =K2*Assumptions!$B$9 -> 1043591.3
A9: Other opex | B9: =B2*Assumptions!$B$10 -> 80000 | C9: =C2*Assumptions!$B$10 -> 89600 | D9: =D2*Assumptions!$B$10 -> 103040 | E9: =E2*Assumptions!$B$10 -> 121587.2 | F9: =F2*Assumptions!$B$10 -> 151984 | G9: =G2*Assumptions!$B$10 -> 189980 | H9: =H2*Assumptions!$B$10 -> 237475 | I9: =I2*Assumptions!$B$10 -> 296843.75 | ... K9: =K2*Assumptions!$B$10 -> 463818.36
A10: Total opex | B10: =SUM(B7:B9) -> 340000 | C10: =SUM(C7:C9) -> 380800 | D10: =SUM(D7:D9) -> 437920 | E10: =SUM(E7:E9) -> 516745.6 | F10: =SUM(F7:F9) -> 645932 | G10: =SUM(G7:G9) -> 807415 | H10: =SUM(H7:H9) -> 1009268.8 | I10: =SUM(I7:I9) -> 1261585.9 | ... K10: =SUM(K7:K9) -> 1971228
A11: EBITDA | B11: =B5-B10 -> 60000 | C11: =C5-C10 -> 67200 | D11: =D5-D10 -> 77280 | E11: =E5-E10 -> 91190.4 | F11: =F5-F10 -> 113988 | G11: =G5-G10 -> 142485 | H11: =H5-H10 -> 178106.25 | I11: =I5-I10 -> 222632.81 | ... K11: =K5-K10 -> 347863.77
A13: Depreciation | B13: =B19*0.2 -> 14000 | C13: =C19*0.2 -> 15680 | D13: =D19*0.2 -> 18032 | E13: =E19*0.2 -> 21277.76 | F13: =F19*0.2 -> 26597.2 | G13: =G19*0.2 -> 21372.75 | H13: =H19*0.2 -> 26715.938 | I13: =I19*0.2 -> 33394.922 | ... K13: =K19*0.2 -> 52179.565
A14: EBIT | B14: =B11-B13 -> 46000 | C14: =C11-C13 -> 51520 | D14: =D11-D13 -> 59248 | E14: =E11-E13 -> 69912.64 | F14: =F11-F13 -> 87390.8 | G14: =G11-G13 -> 121112.25 | H14: =H11-H13 -> 151390.31 | I14: =I11-I13 -> 189237.89 | ... K14: =K11-K13 -> 295684.2
A16: Tax | B16: =B14*Assumptions!$B$13 -> 9200 | C16: =C14*Assumptions!$B$13 -> 10304 | D16: =D14*Assumptions!$B$13 -> 11849.6 | E16: =E14*Assumptions!$B$13 -> 13982.528 | F16: =F14*Assumptions!$B$13 -> 17478.16 | G16: =G14*Assumptions!$B$13 -> 24222.45 | H16: =H14*Assumptions!$B$13 -> 30278.062 | I16: =I14*Assumptions!$B$13 -> 37847.578 | ... K16: =K14*Assumptions!$B$13 -> 59136.841
A17: Net income | B17: =B14-B16 -> 36800 | C17: =C14-C16 -> 41216 | D17: =D14-D16 -> 47398.4 | E17: =E14-E16 -> 55930.112 | F17: =F14-F16 -> 69912.64 | G17: =G14-G16 -> 96889.8 | H17: =H14-H16 -> 121112.25 | I17: =I14-I16 -> 151390.31 | ... K17: =K14-K16 -> 236547.36
A19: Capex | B19: =B2*Assumptions!$B$11 -> 70000 | C19: =C2*Assumptions!$B$11 -> 78400 | D19: =D2*Assumptions!$B$11 -> 90160 | E19: =E2*Assumptions!$B$11 -> 106388.8 | F19: =F2*Assumptions!$B$11 -> 132986 | G19: =G2*Assumptions!$B$12 -> 106863.75 | H19: =H2*Assumptions!$B$12 -> 133579.69 | I19: =I2*Assumptions!$B$12 -> 166974.61 | J19: =J2*Assumptions!$B$12 -> 208718.26 | K19: =K2*Assumptions!$B$12 -> 260897.83
A20: Free cash flow | B20: =B17+B13-B19 -> -19200 | C20: =C17+C13-C19 -> -21504 | D20: =D17+D13-D19 -> -24729.6 | E20: =E17+E13-E19 -> -29180.928 | F20: =F17+F13-F19 -> -36476.16 | G20: =G17+G13-G19 -> 11398.8 | H20: =H17+H13-H19 -> 14248.5 | I20: =I17+I13-I19 -> 17810.625 | ... K20: =K17+K13-K19 -> 27829.102
A21: Opening cash | B21: =Assumptions!B14 -> 200000 | C21: =B22 -> 180800 | D21: =C22 -> 159296 | E21: =D22 -> 134566.4 | F21: =E22 -> 105385.47 | G21: =F22 -> 68909.312 | H21: =G22 -> 80308.112 | I21: =H22 -> 94556.612 | J21: =I22 -> 112367.24 | K21: =J22 -> 134630.52
A22: Closing cash | B22: =B20+B21 -> 180800 | C22: =C20+C21 -> 159296 | D22: =D20+D21 -> 134566.4 | E22: =E20+E21 -> 105385.47 | F22: =F20+F21 -> 68909.312 | G22: =G20+G21 -> 80308.112 | H22: =H20+H21 -> 94556.612 | I22: =I20+I21 -> 112367.24 | ... K22: =K20+K21 -> 162459.62

Sheet KPI Dashboard

Sheet Final Report
B1: Introduction and objective
B2: This project develops a 10‑year financial model for a hypothetical company starting with 1,000,000 € of revenue and 200,000 € of opening cash. The objective is to compare a conservative and a growth‑oriented strategy and assess whether the additional risk associated with a more aggressive growth path is compensated by higher long‑term earnings and value creation.
B3: The model is built in Excel with a structured assumptions sheet, two alternative strategic parameter sets, and a linked financial model producing income statement metrics, free cash flow, and cash balances over time.
B4: Strategy design and assumptions
B5: Both strategies share the same starting point (1,000,000 € revenue, 200,000 € cash, 20% tax rate) but differ in growth, profitability, and reinvestment intensity. The table below summarizes the main assumptions.
B6: The conservative strategy assumes moderate revenue growth (5–6% per year) with a 38% gross margin and disciplined spending on marketing (5% of revenue), staff (15%), and capital expenditure (5% of revenue in the first five years, then 3%). The growth strategy targets much higher revenue growth (12–25%), combined with a slightly higher 40% gross margin but also structurally higher operating and capital intensity through increased marketing, staff costs, and capex ratios.
B7: Financial results
B8: Conservative strategy
B9: Under the conservative scenario, revenue grows steadily from 1,000,000 € in year 1 to approximately 1.58 million € in year 10. Gross profit increases in line with revenue, supported by the stable 38% gross margin. Operating expenses (marketing, staff, and other opex) also rise gradually, but EBITDA remains positive and growing throughout the period.
B10: Net income under the conservative strategy increases from 72,000 € in year 1 to about 118,900 € by year 10. Free cash flow is positive in every year, starting at 32,000 € and reaching around 80,900 € in year 10, reflecting both operational profitability and a moderate capex burden. As a result, closing cash improves from 200,000 € at the start of the period to approximately 746,600 € at the end, indicating a strong liquidity position and no need for external financing.
B11: Growth strategy
B12: In the growth scenario, revenue growth rates between 12% and 25% lead to significantly higher revenue levels over the 10‑year horizon compared with the conservative path (based on the same 1,000,000 € starting revenue). The higher 40% gross margin further supports gross profit expansion, but this is partially offset by higher marketing (8% of revenue), staff (18%), and capex ratios.
... B16: The conservative strategy clearly dominates on cash generation and liquidity within the 10‑year window, while the growth strategy delivers higher long‑term earnings and scale at the expense of tighter cash flows.
D17: Metric (10 years) | E17: Conservative | F17: Growth
D18: Year 10 revenue | E18: ≈ 1.58m € | F18: ≈ 5.8m €
D19: Year 10 net income | E19: ≈ 118.9k € | F19: ≈ 236.5k €
D20: Cumulative free cash flow | E20: ≈ 81k € | F20: ≈ 28k €
D21: Year 10 closing cash | E21: ≈ 746.6k € | F21: ≈ 162.5k €
D22: External financing need | E22: Not required in the model | F22: Might be required
B23: Risk–return assessment
B24: Liquidity and financing risk
B25: The conservative strategy generates positive free cash flow in every period and steadily builds a sizeable cash buffer, reducing the probability of a liquidity shortfall. This makes the company resilient to revenue shocks or cost overruns and allows it to remain self‑funded without resorting to debt or equity raises under the modeled assumptions.
B26: By contrast, the growth strategy operates with lower cash accumulation because higher marketing, staff, and investment requirements consume more of the operating cash flow. Although the model as built may still show positive free cash flow overall, the margin of safety is smaller, which increases the risk that a shortfall in revenue growth could force the firm to seek external financing. In practice, this exposes shareholders to dilution risk and the firm to potential refinancing or covenant risk.
B27: Execution and business risk
B28: Aggressive top‑line growth assumptions (up to 25% annually from year 5 onwards) raise execution risk. Achieving this trajectory requires strong market demand, successful commercial execution, and the ability to integrate rapid headcount growth without productivity losses. If actual growth trails the plan, the higher fixed cost base (particularly staff and marketing) could pressure margins and delay the break‑even of incremental investments.
B29: The conservative strategy, with more modest growth expectations and lower fixed cost intensity, is less sensitive to execution shortfalls. Even if revenue growth underperforms the plan, the impact on the firm’s solvency is more limited because operating leverage and capex commitments are lower.
B30: Return potential and time horizon
B31: The growth strategy offers greater upside in terms of long‑term earnings and enterprise scale: larger revenues and higher net income in later years justify a higher potential valuation if growth is achieved. The conservative strategy produces smaller but more predictable earnings and a stronger cash position, which may appeal to investors who prioritize capital preservation and self‑funded growth.
B32: An important nuance is the time horizon. Over the 10‑year modeling period, the conservative strategy “wins” on cumulative free cash flow and liquidity, while the growth strategy only partially realizes its potential, since the benefits of a larger installed base and brand may continue beyond year 10. From a strictly cash‑flow‑based perspective within this horizon, the extra risk of the growth path yields higher net income but not clearly superior cash generation; the full upside would likely materialize over a longer period.
B33: Conclusion
B34: The analysis highlights a classic trade‑off between a conservative, self‑funded growth path and a more aggressive strategy that prioritizes scale and long‑term earnings. The conservative strategy delivers stable free cash flow, steadily increasing net income, and a robust cash position, leading to low liquidity and financing risk. The growth strategy, in contrast, increases both business and financial risk through higher operating leverage and investment needs but offers higher long‑term net income and a larger business footprint if its ambitious growth assumptions are met.
B35: Rather than identifying a single “optimal” strategy, the comparison shows how different risk preferences and financing constraints can rationally lead to different strategic choices, even from the same starting point. Investors with a low risk tolerance or limited access to external capital would likely favor the conservative strategy, while those willing to accept higher short‑term volatility and funding risk in exchange for greater long‑run earnings potential might find the growth strategy attractive.
